pyelastices/__init__.py
pyelastices/__version__.py
pyelastices/api.py
pyelastices/cmdline.py
pyelastices/logo.png
pyelastices/py.typed
pyelastices/utils.py
pyelastices-0.0.3.data/data/LICENSE
pyelastices-0.0.3.dist-info/LICENSE
pyelastices-0.0.3.dist-info/METADATA
pyelastices-0.0.3.dist-info/WHEEL
pyelastices-0.0.3.dist-info/entry_points.txt
pyelastices-0.0.3.dist-info/top_level.txt
pyelastices-0.0.3.dist-info/RECORD
