Metadata-Version: 2.1
Name: pyelastices
Version: 0.0.3
Summary: ✨ Awesome elasticsearch framework that shines ✨
Home-page: https://github.com/szj2ys/pyelastices
Author: szj
Author-email: szj2ys@qq.com
License: MIT
Platform: UNKNOWN
Classifier: Development Status :: 3 - Alpha
Classifier: License :: OSI Approved :: MIT License
Classifier: Programming Language :: Python :: 3
Requires-Python: >=3.5.0
License-File: LICENSE
Requires-Dist: pandas
Requires-Dist: elasticsearch (<8.0)
Requires-Dist: click
Requires-Dist: click-help-colors
